red0orange/__init__.py
red0orange/args.py
red0orange/database.py
red0orange/feishu_database.py
red0orange/file.py
red0orange/image_helper.py
red0orange/plot.py
red0orange/postprocess.py
red0orange/preprocess.py
red0orange/recorder.py
red0orange/utils.py
red0orange/object_detection/__init__.py
red0orange/object_detection/evaluate_helper.py
red0orange/object_detection/file_helper.py
red0orange/object_detection/metrics.py
red0orange/object_detection/plot_helper.py
red0orange/object_detection/utils.py
red0orange-1.0.1.dist-info/LICENSE
red0orange-1.0.1.dist-info/METADATA
red0orange-1.0.1.dist-info/WHEEL
red0orange-1.0.1.dist-info/top_level.txt
red0orange-1.0.1.dist-info/RECORD
