Metadata-Version: 2.1
Name: red0orange
Version: 1.0.1
Summary: red0orange first pypi package
Home-page: https://github.com/red0orange/red0orange
Author: red0orange
Author-email: huangdehao919@gmail.com
License: UNKNOWN
Platform: UNKNOWN
Classifier: Programming Language :: Python :: 3
Classifier: License :: OSI Approved :: MIT License
Classifier: Operating System :: OS Independent
Requires-Python: >=3.6
License-File: LICENSE
